XGenTS/__init__.py
XGenTS/config.py
XGenTS/customexception.py
XGenTS/data/__init__.py
XGenTS/data/datasets.py
XGenTS/data/preprocessors.py
XGenTS/models/__init__.py
XGenTS/models/adversarial_ae/__init__.py
XGenTS/models/adversarial_ae/adversarial_ae_config.py
XGenTS/models/adversarial_ae/adversarial_ae_model.py
XGenTS/models/ae/__init__.py
XGenTS/models/ae/ae_config.py
XGenTS/models/ae/ae_model.py
XGenTS/models/auto_model/__init__.py
XGenTS/models/auto_model/auto_config.py
XGenTS/models/auto_model/auto_model.py
XGenTS/models/base/__init__.py
XGenTS/models/base/base_config.py
XGenTS/models/base/base_model.py
XGenTS/models/base/base_utils.py
XGenTS/models/beta_tc_vae/__init__.py
XGenTS/models/beta_tc_vae/beta_tc_vae_config.py
XGenTS/models/beta_tc_vae/beta_tc_vae_model.py
XGenTS/models/beta_vae/__init__.py
XGenTS/models/beta_vae/beta_vae_config.py
XGenTS/models/beta_vae/beta_vae_model.py
XGenTS/models/ciwae/__init__.py
XGenTS/models/ciwae/ciwae_config.py
XGenTS/models/ciwae/ciwae_model.py
XGenTS/models/disentangled_beta_vae/__init__.py
XGenTS/models/disentangled_beta_vae/disentangled_beta_vae_config.py
XGenTS/models/disentangled_beta_vae/disentangled_beta_vae_model.py
XGenTS/models/factor_vae/__init__.py
XGenTS/models/factor_vae/factor_vae_config.py
XGenTS/models/factor_vae/factor_vae_model.py
XGenTS/models/factor_vae/factor_vae_utils.py
XGenTS/models/hvae/__init__.py
XGenTS/models/hvae/hvae_config.py
XGenTS/models/hvae/hvae_model.py
XGenTS/models/info_vae/__init__.py
XGenTS/models/info_vae/info_vae_config.py
XGenTS/models/info_vae/info_vae_model.py
XGenTS/models/iwae/__init__.py
XGenTS/models/iwae/iwae_config.py
XGenTS/models/iwae/iwae_model.py
XGenTS/models/miwae/__init__.py
XGenTS/models/miwae/miwae_config.py
XGenTS/models/miwae/miwae_model.py
XGenTS/models/msssim_vae/__init__.py
XGenTS/models/msssim_vae/msssim_vae_config.py
XGenTS/models/msssim_vae/msssim_vae_model.py
XGenTS/models/msssim_vae/msssim_vae_utils.py
XGenTS/models/nn/__init__.py
XGenTS-0.1.1.dist-info/LICENSE
XGenTS-0.1.1.dist-info/METADATA
XGenTS-0.1.1.dist-info/WHEEL
XGenTS-0.1.1.dist-info/top_level.txt
XGenTS-0.1.1.dist-info/RECORD
