Metadata-Version: 2.1
Name: XGenTS
Version: 0.1.1
Summary: An eXplainable framework for Generative Time Series in Python
Home-page: https://github.com/XgenTimeSeries/xgen-timeseries
Author: Khalid OUBLAL (S2A team Institut Polytechnique de Paris)
Author-email: khalid.oublal@polytechnique.edu
Project-URL: Bug Tracker, https://github.com/XgenTimeSeries/xgen-timeseries/issues
Classifier: Programming Language :: Python :: 3
Classifier: Programming Language :: Python :: 3.7
Classifier: Programming Language :: Python :: 3.8
Classifier: Programming Language :: Python :: 3.9
Classifier: License :: OSI Approved :: Apache Software License
Classifier: Operating System :: OS Independent
Requires-Python: >=3.7
License-File: LICENSE
Requires-Dist: numpy (==1.19.4)
Requires-Dist: pandas (==1.1.4)
Requires-Dist: scikit-learn (==0.23.2)
Requires-Dist: scipy (==1.5.4)
Requires-Dist: tqdm (==4.54.0)
Requires-Dist: torch (==1.7.0)
Requires-Dist: joblib (==0.17.0)
Requires-Dist: matplotlib (==3.3.3)
Requires-Dist: seaborn (==0.11.1)
Requires-Dist: tensorboard (==2.4.0)
Requires-Dist: pickle5 ; python_version == "3.7.*"
